{
    "hash_value": "00B5C7A6E0F38638",
    "hash_offset": 8693330,
    "hash_size": 2147486887,
    "hash_resource_type": "PRIM",
    "hash_reference_table_size": 13,
    "hash_reference_table_dummy": 0,
    "hash_size_final": 6560,
    "hash_size_in_memory": 4294967295,
    "hash_size_in_video_memory": 4294967295,
    "hash_reference_data": [
        {
            "hash": "[assembly:/_pro/environment/materials/generic/wood/wood_oiled_noseams_a.mi].pc_mi",
            "flag": "5F"
        }
    ]
}